Metadata-Version: 2.1
Name: salaryLedia
Version: 1.0.0
Summary: A package that calculates salary
Author: Ledia Aliu
Author-email: <lediaaliu@gmail.com>
Keywords: salary,SDA
Classifier: Development Status :: 1 - Planning
Classifier: Intended Audience :: Developers
Classifier: Programming Language :: Python :: 3
Classifier: Operating System :: Unix
Classifier: Operating System :: MacOS :: MacOS X
Classifier: Operating System :: Microsoft :: Windows
